README.rst
setup.py
multipserve/__init__.py
multipserve/core_mps.py
multipserve/mpserve.py
multipserve.egg-info/PKG-INFO
multipserve.egg-info/SOURCES.txt
multipserve.egg-info/dependency_links.txt
multipserve.egg-info/entry_points.txt
multipserve.egg-info/top_level.txt