Metadata-Version: 1.1
Name: multipserve
Version: 1.0.6
Summary: Script for using with multiples applications Pyramid
Home-page: https://github.com/marioidival/multipserve
Author: Mario Idival
Author-email: marioidival@gmail.com
License: BSD
Keywords: multipserve pyramid threading
Platform: UNKNOWN
Classifier: Development Status :: 4 - Beta
Classifier: Topic :: Utilities
Classifier: License :: OSI Approved :: GNU General Public License v2 (GPLv2)
Classifier: Framework :: Pyramid
Classifier: Operating System :: Unix
